<XML encoding="UTF-8" standalone="yes" version="1.0">
<foros>

  <anime>
    <titulo>Death Note</titulo>
    <cap>1</cap>
    <iurl>EmperadorOtaku1/videos/423691298451604</iurl>
  </anime>

  <anime>
    <titulo>Death Note</titulo>
    <cap>2</cap>
    <iurl>EmperadorOtaku1/videos/425024618281983</iurl>
  </anime>

  <anime>
    <titulo>Death Note</titulo>
    <cap>3</cap>
    <iurl>EmperadorOtaku1/videos/1505606366242775</iurl>
  </anime>

  <anime>
    <titulo>Death Note</titulo>
    <cap>4</cap>
    <iurl>EmperadorOtaku1/videos/2323562401219117</iurl>
  </anime>

  <anime>
    <titulo>Death Note</titulo>
    <cap>5</cap>
    <iurl>EmperadorOtaku1/videos/466470977427514</iurl>
  </anime>

  <anime>
    <titulo>Death Note</titulo>
    <cap>6</cap>
    <iurl>EmperadorOtaku1/videos/423426811771076</iurl>
  </anime>

  <anime>
    <titulo>Death Note</titulo>
    <cap>7</cap>
    <iurl>EmperadorOtaku1/videos/2431567243740461</iurl>
  </anime>

  <anime>
    <titulo>Death Note</titulo>
    <cap>8</cap>
    <iurl>EmperadorOtaku1/videos/445862109500920</iurl>
  </anime>

  <anime>
    <titulo>Death Note</titulo>
    <cap>9</cap>
    <iurl>EmperadorOtaku1/videos/2019116671729875</iurl>
  </anime>

  <anime>
    <titulo>Death Note</titulo>
    <cap>10</cap>
    <iurl>EmperadorOtaku1/videos/402922813881400</iurl>
  </anime>

  <anime>
    <titulo>Death Note</titulo>
    <cap>11</cap>
    <iurl>EmperadorOtaku1/videos/625992954546497</iurl>
  </anime>

  <anime>
    <titulo>Death Note</titulo>
    <cap>12</cap>
    <iurl>EmperadorOtaku1/videos/2174732469274613</iurl>
  </anime>

  <anime>
    <titulo>Death Note</titulo>
    <cap>13</cap>
    <iurl>EmperadorOtaku1/videos/489047961836082</iurl>
  </anime>

  <anime>
    <titulo>Death Note</titulo>
    <cap>14</cap>
    <iurl>EmperadorOtaku1/videos/1717845458361669</iurl>
  </anime>

  <anime>
    <titulo>Death Note</titulo>
    <cap>15</cap>
    <iurl>EmperadorOtaku1/videos/319870668692417</iurl>
  </anime>

  <anime>
    <titulo>Death Note</titulo>
    <cap>16</cap>
    <iurl>EmperadorOtaku1/videos/2470642522959992</iurl>
  </anime>

  <anime>
    <titulo>Death Note</titulo>
    <cap>17</cap>
    <iurl>EmperadorOtaku1/videos/398101180921088</iurl>
  </anime>

  <anime>
    <titulo>Death Note</titulo>
    <cap>18</cap>
    <iurl>EmperadorOtaku1/videos/435601763922023</iurl>
  </anime>

  <anime>
    <titulo>Death Note</titulo>
    <cap>19</cap>
    <iurl>EmperadorOtaku1/videos/362081887768430</iurl>
  </anime>

  <anime>
    <titulo>Death Note</titulo>
    <cap>20</cap>
    <iurl>EmperadorOtaku1/videos/438119490088335</iurl>
  </anime>

  <anime>
    <titulo>Death Note</titulo>
    <cap>21</cap>
    <iurl>EmperadorOtaku1/videos/594119554432165</iurl>
  </anime>

  <anime>
    <titulo>Death Note</titulo>
    <cap>22</cap>
    <iurl>EmperadorOtaku1/videos/2415411691844962</iurl>
  </anime>

  <anime>
    <titulo>Death Note</titulo>
    <cap>23</cap>
    <iurl>EmperadorOtaku1/videos/420518022124465</iurl>
  </anime>

  <anime>
    <titulo>Death Note</titulo>
    <cap>24</cap>
    <iurl>EmperadorOtaku1/videos/399612247298817</iurl>
  </anime>

  <anime>
    <titulo>Death Note</titulo>
    <cap>25</cap>
    <iurl>EmperadorOtaku1/videos/1381622585303231</iurl>
  </anime>

  <anime>
    <titulo>Death Note</titulo>
    <cap>26</cap>
    <iurl>EmperadorOtaku1/videos/372347036727664</iurl>
  </anime>

  <anime>
    <titulo>Death Note</titulo>
    <cap>27</cap>
    <iurl>EmperadorOtaku1/videos/400022597256994</iurl>
  </anime>

  <anime>
    <titulo>Death Note</titulo>
    <cap>28</cap>
    <iurl>EmperadorOtaku1/videos/381711032551447</iurl>
  </anime>

  <anime>
    <titulo>Death Note</titulo>
    <cap>29</cap>
    <iurl>EmperadorOtaku1/videos/387716028500413</iurl>
  </anime>

  <anime>
    <titulo>Death Note</titulo>
    <cap>30</cap>
    <iurl>EmperadorOtaku1/videos/1778929615543373</iurl>
  </anime>

  <anime>
    <titulo>Death Note</titulo>
    <cap>31</cap>
    <iurl>EmperadorOtaku1/videos/553166891879263</iurl>
  </anime>

  <anime>
    <titulo>Death Note</titulo>
    <cap>32</cap>
    <iurl>EmperadorOtaku1/videos/449390225820877</iurl>
  </anime>

  <anime>
    <titulo>Death Note</titulo>
    <cap>33</cap>
    <iurl>EmperadorOtaku1/videos/2199895770323097</iurl>
  </anime>

  <anime>
    <titulo>Death Note</titulo>
    <cap>34</cap>
    <iurl>EmperadorOtaku1/videos/1099825963538198</iurl>
  </anime>

  <anime>
    <titulo>Death Note</titulo>
    <cap>35</cap>
    <iurl>EmperadorOtaku1/videos/837664879945360</iurl>
  </anime>

  <anime>
    <titulo>Death Note</titulo>
    <cap>36</cap>
    <iurl>EmperadorOtaku1/videos/373012396664220</iurl>
  </anime>

  <anime>
    <titulo>Death Note</titulo>
    <cap>37</cap>
    <iurl>EmperadorOtaku1/videos/295989694683659</iurl>
  </anime>

</foros>
</XML>
